cranial/common/config.py
cranial/common/logger.py
cranial/common/serialize.py
cranial/common/utils.py
cranial_common-0.3.0.dist-info/LICENSE
cranial_common-0.3.0.dist-info/WHEEL
cranial_common-0.3.0.dist-info/METADATA
cranial_common-0.3.0.dist-info/RECORD
